arianna/__init__.py
arianna/autocorr.py
arianna/ensemble.py
arianna/fwrapper.py
arianna/moves.py
arianna/parallel.py
arianna/samples.py
arianna/slice.py
arianna/tools.py
arianna-0.0.1.dist-info/METADATA
arianna-0.0.1.dist-info/WHEEL
arianna-0.0.1.dist-info/top_level.txt
arianna-0.0.1.dist-info/RECORD
